andromolecules/AndroMolecules.py
andromolecules/__init__.py
andromolecules/potentials.py
andomolecules-0.1.dist-info/METADATA
andomolecules-0.1.dist-info/WHEEL
andomolecules-0.1.dist-info/top_level.txt
andomolecules-0.1.dist-info/RECORD
